module_python/__init__.py
module_python/info.py
module_python-0.1.0.dist-info/LICENSE
module_python-0.1.0.dist-info/METADATA
module_python-0.1.0.dist-info/WHEEL
module_python-0.1.0.dist-info/top_level.txt
module_python-0.1.0.dist-info/RECORD
